<annotation>
  <folder>F:\STUDY\Trimester 12\Pattern Lab\Rickshaw Images\images</folder>
  <filename>000771.png</filename>
  <segmented>0</segmented>
  <size>
    <width>480</width>
    <height>320</height>
    <depth>3</depth>
  </size>
  <object>
    <name>Rickshaw</name>
    <pose>Unspecified</pose>
    <truncated>0</truncated>
    <difficult>0</difficult>
    <bndbox>
      <xmin>123</xmin>
      <ymin>49</ymin>
      <xmax>372</xmax>
      <ymax>309</ymax>
    </bndbox>
  </object>
  <object>
    <name>Rickshaw</name>
    <pose>Unspecified</pose>
    <truncated>0</truncated>
    <difficult>0</difficult>
    <bndbox>
      <xmin>388</xmin>
      <ymin>100</ymin>
      <xmax>443</xmax>
      <ymax>175</ymax>
    </bndbox>
  </object>
</annotation>
